MANIFEST.in
README.rst
setup.cfg
setup.py
macaw/__init__.py
macaw/linear.py
macaw/models.py
macaw/objective_functions.py
macaw/optimizers.py
macaw.egg-info/PKG-INFO
macaw.egg-info/SOURCES.txt
macaw.egg-info/dependency_links.txt
macaw.egg-info/requires.txt
macaw.egg-info/top_level.txt