Metadata-Version: 1.1
Name: macaw
Version: 0.2.dev0
Summary: A colorful, long-tailed package for beautiful Majorization-minimization
Home-page: https://github.com/mirca/macaw
Author: mirca
Author-email: jvmirca@gmail.com
License: MIT
Keywords: statistics probability
Platform: UNKNOWN
Classifier: Development Status :: 3 - Alpha
Classifier: Intended Audience :: Science/Research
Classifier: License :: OSI Approved :: MIT License
Classifier: Programming Language :: Python :: 3.6
